spriteutilNhungLai/__init__.py
spriteutilNhungLai/spriteutil.py
spriteutilNhungLai-1.0.1.dist-info/LICENSE
spriteutilNhungLai-1.0.1.dist-info/METADATA
spriteutilNhungLai-1.0.1.dist-info/WHEEL
spriteutilNhungLai-1.0.1.dist-info/top_level.txt
spriteutilNhungLai-1.0.1.dist-info/RECORD
